actions_includes/__init__.py
actions_includes/__main__.py
actions_includes/check.py
actions_includes/expressions.py
actions_includes/files.py
actions_includes/output.py
actions_includes/version.py
actions_includes/yaml_map.py
actions_includes-0.0.post150.dist-info/licenses/LICENSE
actions_includes-0.0.post150.dist-info/METADATA
actions_includes-0.0.post150.dist-info/WHEEL
actions_includes-0.0.post150.dist-info/entry_points.txt
actions_includes-0.0.post150.dist-info/top_level.txt
actions_includes-0.0.post150.dist-info/zip-safe
actions_includes-0.0.post150.dist-info/RECORD
