Metadata-Version: 2.4
Name: actions-includes
Version: 0.0.post150
Summary: Tool for flattening include statements in GitHub actions workflow.yml files.
Home-page: https://github.com/mithro/actions-includes
Author: Tim 'mithro' Ansell
Author-email: tansell@google.com
License: Apache 2.0
Project-URL: Bug Tracker, https://github.com/mithro/actions-includes/issues
Project-URL: Source Code, https://github.com/mithro/actions-includes
Classifier: Programming Language :: Python :: 3
Classifier: License :: OSI Approved :: Apache Software License
Classifier: Operating System :: OS Independent
Requires-Python: >=3.8
License-File: LICENSE
Requires-Dist: ruamel.yaml<0.18
Dynamic: author
Dynamic: author-email
Dynamic: classifier
Dynamic: description
Dynamic: description-content-type
Dynamic: home-page
Dynamic: license
Dynamic: license-file
Dynamic: project-url
Dynamic: requires-dist
Dynamic: requires-python
Dynamic: summary
